laptimize/__init__.py
laptimize/branch_and_bound_solver.py
laptimize/curve_approximation.py
laptimize/examples.py
laptimize/lap_model.py
laptimize/log.py
laptimize/solver.py
laptimize/temp_solver.py
laptimize/test.py
laptimize/test/__init__.py
laptimize/test/test_branch_and_bound_solver.py
laptimize/test/test_curve_approximation.py
laptimize/test/test_lap_model.py
laptimize/test/test_solver.py
laptimize-1.0.1.dist-info/LICENSE
laptimize-1.0.1.dist-info/METADATA
laptimize-1.0.1.dist-info/WHEEL
laptimize-1.0.1.dist-info/top_level.txt
laptimize-1.0.1.dist-info/RECORD
