Metadata-Version: 2.1
Name: laptimize
Version: 1.0.1
Summary: package to solve separable non linear optimization problems
Home-page: UNKNOWN
Author: Ishanga Udatiyawala
Author-email: uichathurika@gmail.com
License: UNKNOWN
Keywords: python,nonlinear optimization,separable programming,branch and bound,global solution
Platform: UNKNOWN
Classifier: Development Status :: 3 - Alpha
Classifier: Intended Audience :: Education
Classifier: Programming Language :: Python :: 3.6
Classifier: Operating System :: Microsoft :: Windows
Classifier: Natural Language :: English
Classifier: Topic :: Scientific/Engineering :: Mathematics
Requires-Dist: numpy (>=1.19.2)
Requires-Dist: pandas (>=1.1.3)
Requires-Dist: pulp (>=2.3)
